pytolino/__init__.py
pytolino/servers_settings.ini
pytolino/tolino_cloud.py
pytolino-1.7.dist-info/licenses/LICENSE
pytolino-1.7.dist-info/METADATA
pytolino-1.7.dist-info/WHEEL
pytolino-1.7.dist-info/top_level.txt
pytolino-1.7.dist-info/RECORD
