Metadata-Version: 2.4
Name: pytolino
Version: 1.7
Summary: client for tolino cloud
Author: Imam Usmani
Project-URL: Source Code, https://github.com/ImamAzim/pytolino
Project-URL: Documentation, https://pytolino.readthedocs.io/en/latest/index.html
Classifier: Intended Audience :: Developers
Classifier: License :: OSI Approved :: GNU General Public License v3 (GPLv3)
Classifier: Natural Language :: English
Classifier: Programming Language :: Python :: 3
Classifier: Operating System :: POSIX :: Linux
Requires-Python: >=3.7
License-File: LICENSE
Requires-Dist: requests
Requires-Dist: mechanize
Provides-Extra: dev
Requires-Dist: pytest; extra == "dev"
Requires-Dist: flake8; extra == "dev"
Requires-Dist: ipython; extra == "dev"
Requires-Dist: sphinx; extra == "dev"
Requires-Dist: build; extra == "dev"
Requires-Dist: twine; extra == "dev"
Requires-Dist: sphinx-rtd-theme; extra == "dev"
Dynamic: license-file
